Metadata-Version: 2.1
Name: BatchAdapt
Version: 1.2
Summary: Dynamic multi-loci/multi-repeat tract microsatellite reference sequence generator
Home-page: https://github.com/helloabunai/Batchadapt
Author: Alastair Maxwell/University of Glasgow
Author-email: alastair.maxwell@glasgow.ac.uk
License: GPLv3
Keywords: XML FASTA Genetic-references Bioinformatics Data-analysis
Platform: UNKNOWN
Classifier: Development Status :: 2 - Pre-Alpha
Classifier: Intended Audience :: Education
Classifier: Intended Audience :: End Users/Desktop
Classifier: Intended Audience :: Science/Research
Classifier: License :: OSI Approved :: GNU General Public License v3 (GPLv3)
Classifier: Programming Language :: Python :: 3.6
Classifier: Programming Language :: Python :: 3.7
Classifier: Environment :: Console
Classifier: Operating System :: MacOS :: MacOS X
Classifier: Operating System :: POSIX
Requires-Python: >3.7
